{"validation_loss": 389.2691955566406, "time_this_iter_s": 291.9984254837036, "done": false, "training_iteration": 1, "trial_id": "0f7456ed", "date": "2023-08-19_22-26-21", "timestamp": 1692483981, "time_total_s": 291.9984254837036, "pid": 8745, "hostname": "ip-172-31-38-240", "node_ip": "172.31.38.240", "config": {"n_hidden": 512, "n_layers": 1, "n_latent": 50, "lr": 0.01, "batch_size": 1024, "var_activation": "<built-in function softplus>"}, "time_since_restore": 291.9984254837036, "iterations_since_restore": 1}
{"validation_loss": 387.6055908203125, "time_this_iter_s": 270.07265424728394, "done": false, "training_iteration": 2, "trial_id": "0f7456ed", "date": "2023-08-19_22-30-51", "timestamp": 1692484251, "time_total_s": 562.0710797309875, "pid": 8745, "hostname": "ip-172-31-38-240", "node_ip": "172.31.38.240", "config": {"n_hidden": 512, "n_layers": 1, "n_latent": 50, "lr": 0.01, "batch_size": 1024, "var_activation": "<built-in function softplus>"}, "time_since_restore": 562.0710797309875, "iterations_since_restore": 2}
{"validation_loss": 388.7996826171875, "time_this_iter_s": 271.0548393726349, "done": false, "training_iteration": 3, "trial_id": "0f7456ed", "date": "2023-08-19_22-35-22", "timestamp": 1692484522, "time_total_s": 833.1259191036224, "pid": 8745, "hostname": "ip-172-31-38-240", "node_ip": "172.31.38.240", "config": {"n_hidden": 512, "n_layers": 1, "n_latent": 50, "lr": 0.01, "batch_size": 1024, "var_activation": "<built-in function softplus>"}, "time_since_restore": 833.1259191036224, "iterations_since_restore": 3}
{"validation_loss": 387.5411376953125, "time_this_iter_s": 271.52855587005615, "done": false, "training_iteration": 4, "trial_id": "0f7456ed", "date": "2023-08-19_22-39-54", "timestamp": 1692484794, "time_total_s": 1104.6544749736786, "pid": 8745, "hostname": "ip-172-31-38-240", "node_ip": "172.31.38.240", "config": {"n_hidden": 512, "n_layers": 1, "n_latent": 50, "lr": 0.01, "batch_size": 1024, "var_activation": "<built-in function softplus>"}, "time_since_restore": 1104.6544749736786, "iterations_since_restore": 4}
{"validation_loss": 388.1686096191406, "time_this_iter_s": 272.66219782829285, "done": false, "training_iteration": 5, "trial_id": "0f7456ed", "date": "2023-08-19_22-44-26", "timestamp": 1692485066, "time_total_s": 1377.3166728019714, "pid": 8745, "hostname": "ip-172-31-38-240", "node_ip": "172.31.38.240", "config": {"n_hidden": 512, "n_layers": 1, "n_latent": 50, "lr": 0.01, "batch_size": 1024, "var_activation": "<built-in function softplus>"}, "time_since_restore": 1377.3166728019714, "iterations_since_restore": 5}
{"validation_loss": 389.3079528808594, "time_this_iter_s": 277.25908064842224, "done": false, "training_iteration": 6, "trial_id": "0f7456ed", "date": "2023-08-19_22-49-04", "timestamp": 1692485344, "time_total_s": 1654.5757534503937, "pid": 8745, "hostname": "ip-172-31-38-240", "node_ip": "172.31.38.240", "config": {"n_hidden": 512, "n_layers": 1, "n_latent": 50, "lr": 0.01, "batch_size": 1024, "var_activation": "<built-in function softplus>"}, "time_since_restore": 1654.5757534503937, "iterations_since_restore": 6}
{"validation_loss": 391.00372314453125, "time_this_iter_s": 270.6272451877594, "done": false, "training_iteration": 7, "trial_id": "0f7456ed", "date": "2023-08-19_22-53-34", "timestamp": 1692485614, "time_total_s": 1925.202998638153, "pid": 8745, "hostname": "ip-172-31-38-240", "node_ip": "172.31.38.240", "config": {"n_hidden": 512, "n_layers": 1, "n_latent": 50, "lr": 0.01, "batch_size": 1024, "var_activation": "<built-in function softplus>"}, "time_since_restore": 1925.202998638153, "iterations_since_restore": 7}
{"validation_loss": 389.76080322265625, "time_this_iter_s": 267.65825724601746, "done": true, "training_iteration": 8, "trial_id": "0f7456ed", "date": "2023-08-19_22-58-02", "timestamp": 1692485882, "time_total_s": 2192.8612558841705, "pid": 8745, "hostname": "ip-172-31-38-240", "node_ip": "172.31.38.240", "config": {"n_hidden": 512, "n_layers": 1, "n_latent": 50, "lr": 0.01, "batch_size": 1024, "var_activation": "<built-in function softplus>"}, "time_since_restore": 2192.8612558841705, "iterations_since_restore": 8}
